{"commitInfo":{"timestamp":1777372879715,"operation":"STREAMING UPDATE","operationParameters":{"outputMode":"Append","queryId":"4874fc42-81d5-4195-8650-8080d91d1614","epochId":"40"},"readVersion":39,"isolationLevel":"Serializable","isBlindAppend":true,"operationMetrics":{"numRemovedFiles":"0","numOutputRows":"0","numOutputBytes":"0","numAddedFiles":"0"},"engineInfo":"Apache-Spark/3.4.1 Delta-Lake/2.4.0","txnId":"ac460c4c-94df-4aaa-8f2b-987244d9db9f"}}
{"txn":{"appId":"4874fc42-81d5-4195-8650-8080d91d1614","version":40,"lastUpdated":1777372879712}}
